{
  "resources": [
    {
      "path": "data.csv",
      "name": "data",
      "profile": "tabular-data-resource",
      "scheme": "file",
      "format": "csv",
      "hashing": "md5",
      "encoding": "utf-8",
      "schema": {
        "fields": [
          {
            "name": "Year",
            "type": "integer",
            "title": "Year"
          },
          {
            "name": "SeriesCode",
            "type": "string",
            "constraints": {
              "enum": [
                "DC_TOF_TRDDBML",
                ""
              ]
            },
            "title": "SeriesCode"
          },
          {
            "name": "GeoAreaName",
            "type": "string",
            "constraints": {
              "enum": [
                "Mexico",
                "Albania",
                "Moldova",
                "Montenegro",
                "Azerbaijan",
                "Armenia",
                "Bosnia and Herzegovina",
                "Serbia",
                "Belarus",
                "Viet Nam",
                "Tajikistan",
                "Chile",
                "China",
                "Colombia",
                "Türkiye",
                "Turkmenistan",
                "Ukraine",
                "North Macedonia",
                "Uzbekistan",
                "Costa Rica",
                "Croatia",
                "Georgia",
                "India",
                "Kazakhstan",
                "Kyrgyzstan",
                ""
              ]
            },
            "title": "Country"
          },
          {
            "name": "Value",
            "type": "number",
            "title": "Value"
          }
        ]
      }
    }
  ],
  "profile": "data-package",
  "name": "8-a-1-DC_TOF_TRDDBML",
  "title": "Total official flows (disbursement) for Aid for Trade, by recipient countries (millions of constant 2021 United States dollars)"
}