{"data":{"Year":[2022,2022,2022,2022,2022,2022,2022,2022,2022,2022,2022,2022,2022,2022,2022,2022,2022,2022,2022,2022,2022,2022,2022,2022,2022,2022,2022,2022,2022,2022,2022,2022,2022,2022,2022,2022,2022,2022,2022,2022,2022,2022,2022,2022,2022,2022,2022,2022,2022,2022,2022,2022,2022,2022,2022,2022,2022,2022,2022,2022,2022,2022,2022,2022,2022,2022,2022,2022,2022,2022,2022,2022,2022,2022,2022,2022,2022,2022,2022,2022,2022,2022,2022],"SeriesCode":["SP_PSR_SATIS_PRM","SP_PSR_SATIS_PRM","SP_PSR_SATIS_PRM","SP_PSR_SATIS_PRM","SP_PSR_SATIS_PRM","SP_PSR_SATIS_PRM","SP_PSR_SATIS_PRM","SP_PSR_SATIS_PRM","SP_PSR_SATIS_PRM","SP_PSR_SATIS_PRM","SP_PSR_SATIS_PRM","SP_PSR_SATIS_PRM","SP_PSR_SATIS_PRM","SP_PSR_SATIS_PRM","SP_PSR_SATIS_PRM","SP_PSR_SATIS_PRM","SP_PSR_SATIS_PRM","SP_PSR_SATIS_PRM","SP_PSR_SATIS_PRM","SP_PSR_SATIS_PRM","SP_PSR_SATIS_PRM","SP_PSR_SATIS_PRM","SP_PSR_SATIS_PRM","SP_PSR_SATIS_PRM","SP_PSR_SATIS_PRM","SP_PSR_SATIS_PRM","SP_PSR_SATIS_PRM","SP_PSR_SATIS_PRM","SP_PSR_SATIS_PRM","SP_PSR_SATIS_PRM","SP_PSR_SATIS_PRM","SP_PSR_SATIS_PRM","SP_PSR_SATIS_PRM","SP_PSR_SATIS_PRM","SP_PSR_SATIS_PRM","SP_PSR_SATIS_PRM","SP_PSR_SATIS_PRM","SP_PSR_SATIS_PRM","SP_PSR_SATIS_PRM","SP_PSR_SATIS_PRM","SP_PSR_SATIS_PRM","SP_PSR_SATIS_PRM","SP_PSR_SATIS_PRM","SP_PSR_SATIS_PRM","SP_PSR_SATIS_PRM","SP_PSR_SATIS_PRM","SP_PSR_SATIS_PRM","SP_PSR_SATIS_PRM","SP_PSR_SATIS_PRM","SP_PSR_SATIS_PRM","SP_PSR_SATIS_PRM","SP_PSR_SATIS_PRM","SP_PSR_SATIS_PRM","SP_PSR_SATIS_PRM","SP_PSR_SATIS_PRM","SP_PSR_SATIS_PRM","SP_PSR_SATIS_PRM","SP_PSR_SATIS_PRM","SP_PSR_SATIS_PRM","SP_PSR_SATIS_PRM","SP_PSR_SATIS_PRM","SP_PSR_SATIS_PRM","SP_PSR_SATIS_PRM","SP_PSR_SATIS_PRM","SP_PSR_SATIS_PRM","SP_PSR_SATIS_PRM","SP_PSR_SATIS_PRM","SP_PSR_SATIS_PRM","SP_PSR_SATIS_PRM","SP_PSR_SATIS_PRM","SP_PSR_SATIS_PRM","SP_PSR_SATIS_PRM","SP_PSR_SATIS_PRM","SP_PSR_SATIS_PRM","SP_PSR_SATIS_PRM","SP_PSR_SATIS_PRM","SP_PSR_SATIS_PRM","SP_PSR_SATIS_PRM","SP_PSR_SATIS_PRM","SP_PSR_SATIS_PRM","SP_PSR_SATIS_PRM","SP_PSR_SATIS_PRM","SP_PSR_SATIS_PRM"],"GeoAreaName":["Belarus","Belarus","Belarus","Belarus","Belarus","Belarus","Belarus","Belarus","Belarus","Belarus","Belarus","Belarus","Belarus","Belarus","Belarus","Belarus","Belarus","Belarus","Belarus","Belarus","Belarus","Belarus","Belarus","Belarus","Belarus","Belarus","Belarus","Belarus","Belarus","Belarus","Israel","Israel","Israel","Israel","Israel","Israel","Israel","Israel","Israel","Israel","Israel","Israel","Mexico","Mexico","Mexico","Mexico","Mexico","Mexico","Mexico","Mexico","Mexico","Mexico","Mexico","Mexico","Mexico","Mexico","Mexico","Mexico","Mexico","Mexico","Mexico","Mexico","Mexico","Mexico","Mexico","Mexico","Mexico","Mexico","Mexico","Mexico","Mexico","Mexico","Mexico","Mexico","Mexico","Mexico","Mexico","Mexico","Mexico","Mexico","Mexico","Mexico","Mexico"],"Age":["ALLAGE","ALLAGE","ALLAGE","ALLAGE","ALLAGE","ALLAGE","ALLAGE","ALLAGE","ALLAGE","ALLAGE","ALLAGE","ALLAGE","ALLAGE","ALLAGE","ALLAGE","ALLAGE","ALLAGE","ALLAGE","ALLAGE","ALLAGE","ALLAGE","ALLAGE","ALLAGE","ALLAGE","ALLAGE","ALLAGE","ALLAGE","ALLAGE","ALLAGE","ALLAGE","ALLAGE","ALLAGE","ALLAGE","ALLAGE","ALLAGE","ALLAGE","ALLAGE","ALLAGE","ALLAGE","ALLAGE","ALLAGE","ALLAGE","ALLAGE","25-34","45-54","ALLAGE","ALLAGE","ALLAGE","ALLAGE","ALLAGE","ALLAGE","ALLAGE","ALLAGE","ALLAGE","ALLAGE","65+","ALLAGE","65+","25-34","35-44","35-44","35-44","35-44","55-64","45-54","45-54","55-64","25-34","45-54","ALLAGE","ALLAGE","ALLAGE","ALLAGE","55-64","<25Y","55-64","<25Y","<25Y","65+","<25Y","25-34","65+","65+"],"Disability status":["_T","_T","_T","_T","_T","_T","_T","_T","_T","_T","_T","_T","_T","_T","_T","_T","_T","_T","_T","_T","_T","_T","_T","_T","_T","_T","_T","_T","_T","_T","_T","_T","_T","_T","_T","_T","_T","_T","_T","_T","_T","_T","_T","_T","_T","_T","_T","_T","_T","_T","_T","_T","_T","_T","_T","_T","_T","_T","_T","_T","_T","_T","_T","_T","_T","_T","_T","_T","_T","_T","_T","_T","_T","_T","_T","_T","_T","_T","_T","_T","_T","_T","_T"],"Location":["ALLAREA","ALLAREA","ALLAREA","ALLAREA","ALLAREA","ALLAREA","ALLAREA","URBAN","RURAL","RURAL","RURAL","RURAL","RURAL","RURAL","ALLAREA","URBAN","ALLAREA","ALLAREA","ALLAREA","ALLAREA","ALLAREA","ALLAREA","URBAN","URBAN","URBAN","URBAN","ALLAREA","ALLAREA","ALLAREA","ALLAREA","ALLAREA","ALLAREA","ALLAREA","ALLAREA","ALLAREA","ALLAREA","ALLAREA","ALLAREA","ALLAREA","ALLAREA","ALLAREA","ALLAREA","ALLAREA","ALLAREA","ALLAREA","ALLAREA","ALLAREA","ALLAREA","ALLAREA","ALLAREA","ALLAREA","ALLAREA","ALLAREA","ALLAREA","ALLAREA","ALLAREA","ALLAREA","ALLAREA","ALLAREA","ALLAREA","ALLAREA","ALLAREA","ALLAREA","ALLAREA","ALLAREA","ALLAREA","ALLAREA","ALLAREA","ALLAREA","URBAN","URBAN","URBAN","URBAN","ALLAREA","ALLAREA","ALLAREA","ALLAREA","ALLAREA","ALLAREA","ALLAREA","ALLAREA","ALLAREA","ALLAREA"],"Population Group":["TOTAL","TOTAL","TOTAL","TOTAL","TOTAL","TOTAL","TOTAL","TOTAL","TOTAL","TOTAL","TOTAL","TOTAL","TOTAL","TOTAL","TOTAL","TOTAL","TOTAL","TOTAL","TOTAL","TOTAL","TOTAL","TOTAL","TOTAL","TOTAL","TOTAL","TOTAL","TOTAL","TOTAL","TOTAL","TOTAL","TOTAL","TOTAL","TOTAL","TOTAL","TOTAL","POP_A","POP_A","POP_A","TOTAL","TOTAL","TOTAL","TOTAL","TOTAL","TOTAL","TOTAL","TOTAL","TOTAL","TOTAL","TOTAL","TOTAL","TOTAL","TOTAL","TOTAL","TOTAL","TOTAL","TOTAL","TOTAL","TOTAL","TOTAL","TOTAL","TOTAL","TOTAL","TOTAL","TOTAL","TOTAL","TOTAL","TOTAL","TOTAL","TOTAL","TOTAL","TOTAL","TOTAL","TOTAL","TOTAL","TOTAL","TOTAL","TOTAL","TOTAL","TOTAL","TOTAL","TOTAL","TOTAL","TOTAL"],"Quantile":[null,null,null,null,null,null,null,null,null,null,null,null,null,null,null,null,null,null,null,null,null,null,null,null,null,null,null,null,null,null,null,null,null,null,null,null,null,null,null,null,null,null,null,null,null,null,null,null,null,null,null,null,null,null,null,null,null,null,null,null,null,null,null,null,null,null,null,null,null,null,null,null,null,null,null,null,null,null,null,null,null,null,null],"Service Attribute":["QUALITY","EQUALITY","ATTITUDE","AVERAGE","ACCESS","AFFORD","QUALITY","AVERAGE","ACCESS","AFFORD","QUALITY","EQUALITY","ATTITUDE","AVERAGE","ACCESS","ACCESS","AFFORD","EQUALITY","ATTITUDE","AVERAGE","ATTITUDE","AVERAGE","AFFORD","QUALITY","ATTITUDE","EQUALITY","ACCESS","AFFORD","QUALITY","EQUALITY","QUALITY","ATTITUDE","ACCESS","QUALITY","ATTITUDE","ACCESS","QUALITY","ATTITUDE","ACCESS","ATTITUDE","ACCESS","QUALITY","QUALITY","ATTITUDE","AVERAGE","AVERAGE","AFFORD","QUALITY","ATTITUDE","AVERAGE","AFFORD","ATTITUDE","AVERAGE","AFFORD","QUALITY","QUALITY","ATTITUDE","AVERAGE","AVERAGE","AFFORD","QUALITY","ATTITUDE","AVERAGE","AVERAGE","AFFORD","QUALITY","ATTITUDE","QUALITY","ATTITUDE","AFFORD","QUALITY","ATTITUDE","AVERAGE","AFFORD","AFFORD","QUALITY","QUALITY","ATTITUDE","ATTITUDE","AVERAGE","AFFORD","AFFORD","AFFORD"],"Sex":["BOTHSEX","BOTHSEX","BOTHSEX","BOTHSEX","MALE","MALE","MALE","BOTHSEX","BOTHSEX","BOTHSEX","BOTHSEX","BOTHSEX","BOTHSEX","BOTHSEX","BOTHSEX","BOTHSEX","BOTHSEX","MALE","MALE","MALE","FEMALE","FEMALE","BOTHSEX","BOTHSEX","BOTHSEX","BOTHSEX","FEMALE","FEMALE","FEMALE","FEMALE","MALE","MALE","FEMALE","FEMALE","FEMALE","BOTHSEX","BOTHSEX","BOTHSEX","MALE","BOTHSEX","BOTHSEX","BOTHSEX","MALE","BOTHSEX","BOTHSEX","FEMALE","BOTHSEX","BOTHSEX","BOTHSEX","BOTHSEX","MALE","MALE","MALE","FEMALE","FEMALE","BOTHSEX","FEMALE","BOTHSEX","BOTHSEX","BOTHSEX","BOTHSEX","BOTHSEX","BOTHSEX","BOTHSEX","BOTHSEX","BOTHSEX","BOTHSEX","BOTHSEX","BOTHSEX","BOTHSEX","BOTHSEX","BOTHSEX","BOTHSEX","BOTHSEX","BOTHSEX","BOTHSEX","BOTHSEX","BOTHSEX","BOTHSEX","BOTHSEX","BOTHSEX","BOTHSEX","BOTHSEX"],"Value":[92,91,92,92,97,90,92,91,99,90,98,93,96,95,98,98,88,90,91,92,93,92,88,90,91,90,98,86,92,91,71,76,80,66,75,75,66,67,81,75,80,68,73,79,65,63,45,70,78,64,48,79,66,43,68,73,77,65,65,44,67,76,62,67,44,73,82,69,78,45,70,78,64,46,46,74,76,81,75,67,46,46,46]},"edges":{"From":["SeriesCode","GeoAreaName","Age","Disability status","Location","Population Group","Service Attribute"],"To":["GeoAreaName","Age","Disability status","Location","Population Group","Service Attribute","Sex"]}}