{"Year":[2022,2022,2022,2022,2022,2022,2022,2022,2022,2022],"SeriesCode":["SP_PSR_OSATIS_SEC","SP_PSR_OSATIS_SEC","SP_PSR_OSATIS_SEC","SP_PSR_OSATIS_SEC","SP_PSR_OSATIS_SEC","SP_PSR_OSATIS_SEC","SP_PSR_OSATIS_SEC","SP_PSR_OSATIS_SEC","SP_PSR_OSATIS_SEC","SP_PSR_OSATIS_SEC"],"\u0421\u0442\u0440\u0430\u043d\u0430 ":["Belarus","Belarus","Belarus","Belarus","Belarus","Israel","Israel","Israel","Israel","Israel"],"Age":["ALLAGE","ALLAGE","ALLAGE","ALLAGE","ALLAGE","ALLAGE","ALLAGE","ALLAGE","ALLAGE","ALLAGE"],"Disability status":["_T","_T","_T","_T","_T","_T","_T","_T","_T","_T"],"Location":["ALLAREA","ALLAREA","RURAL","URBAN","ALLAREA","ALLAREA","ALLAREA","ALLAREA","ALLAREA","ALLAREA"],"Population Group":["TOTAL","TOTAL","TOTAL","TOTAL","TOTAL","TOTAL","TOTAL","TOTAL","POP_A","POP_A"],"Quantile":[null,null,null,null,null,null,null,null,null,null],"Sex":["BOTHSEX","FEMALE","BOTHSEX","BOTHSEX","MALE","BOTHSEX","FEMALE","MALE","BOTHSEX","BOTHSEX"],"Value":[89,89,91,88,89,80,81,79,68,68]}