{
  "resources": [
    {
      "path": "data.csv",
      "name": "data",
      "profile": "tabular-data-resource",
      "scheme": "file",
      "format": "csv",
      "hashing": "md5",
      "encoding": "utf-8",
      "schema": {
        "fields": [
          {
            "name": "Year",
            "type": "integer",
            "title": "Year"
          },
          {
            "name": "SeriesCode",
            "type": "string",
            "constraints": {
              "enum": [
                "ER_H2O_RURP",
                ""
              ]
            },
            "title": "SeriesCode"
          },
          {
            "name": "GeoAreaName",
            "type": "string",
            "constraints": {
              "enum": [
                "Hungary",
                "India",
                "Italy",
                "Kazakhstan",
                "Kyrgyzstan",
                "Lithuania",
                "Mexico",
                "Moldova",
                "Montenegro",
                "Netherlands (Kingdom of the)",
                "New Zealand",
                "Norway",
                "Romania",
                "Serbia",
                "Viet Nam",
                "Tajikistan",
                "Albania",
                "Azerbaijan",
                "Austria",
                "Bosnia and Herzegovina",
                "Belarus",
                "Chile",
                "China",
                "Colombia",
                "Costa Rica",
                "Croatia",
                "Estonia",
                "Georgia",
                "Turkmenistan",
                "Ukraine",
                "Greece",
                "North Macedonia",
                "Uzbekistan",
                ""
              ]
            },
            "title": "Country"
          },
          {
            "name": "Location",
            "type": "string",
            "constraints": {
              "enum": [
                "Rural",
                ""
              ]
            },
            "title": "Location"
          },
          {
            "name": "Value",
            "type": "number",
            "title": "Value"
          }
        ]
      }
    }
  ],
  "profile": "data-package",
  "name": "6-b-1-ER_H2O_RURP",
  "title": "Countries with users/communities participating in planning programs in rural drinking-water supply, by level of participation (3 = High; 2 = Moderate; 1 = Low; 0 = NA)"
}